pythonautogui/__init__.py
pythonautogui/internals.py
pythonautogui/overrides.py
pythonautogui-0.0.2.dist-info/METADATA
pythonautogui-0.0.2.dist-info/WHEEL
pythonautogui-0.0.2.dist-info/entry_points.txt
pythonautogui-0.0.2.dist-info/RECORD
