Metadata-Version: 2.1
Name: pythonautogui
Version: 0.0.2
Summary: Generate a Tkinter GUI from any Python program
Project-URL: Bug Tracker, https://github.com/Cutwell/python-auto-gui/issues
Project-URL: Homepage, https://github.com/Cutwell/python-auto-gui
Author-email: Zachary Smith <zachsmith.dev@gmail.com>
Classifier: License :: OSI Approved :: MIT License
Classifier: Operating System :: OS Independent
Classifier: Programming Language :: Python :: 3
Requires-Python: >=3.10
